<users>
	<user>
		<username>admin</username>
		<password>test</password>
		<hazards>true</hazards>
		<weather>true</weather>
		<speedlimit>true</speedlimit>
		<admin>true</admin>
	</user>
	<user>
		<username>test</username>
		<password>test</password>
		<hazards>false</hazards>
		<weather>false</weather>
		<speedlimit>false</speedlimit>
		<admin>false</admin>
	</user>
	<user>
		<username>cri</username>
		<password>test</password>
		<hazards>false</hazards>
		<weather>false</weather>
		<speedlimit>false</speedlimit>
		<admin>false</admin>
	</user>
	<user>
		<username>f</username>
		<password>f</password>
		<hazards>false</hazards>
		<weather>false</weather>
		<speedlimit>false</speedlimit>
		<admin>false</admin>
	</user>
</users>

